denonavr3312/__init__.py
denonavr3312/classes/__init__.py
denonavr3312/classes/avr.py
denonavr3312/classes/commands.py
denonavr3312-0.2.0.dist-info/DESCRIPTION.rst
denonavr3312-0.2.0.dist-info/METADATA
denonavr3312-0.2.0.dist-info/RECORD
denonavr3312-0.2.0.dist-info/WHEEL
denonavr3312-0.2.0.dist-info/metadata.json
denonavr3312-0.2.0.dist-info/top_level.txt
