Metadata-Version: 2.0
Name: denonavr3312
Version: 0.2.0
Summary: Control Denon AVR 3312 through telnet interface
Home-page: https://github.com/gyzpunk/denonavr3312
Author: Florent Captier
Author-email: florent@captier.org
License: GNU
Platform: any
Classifier: Development Status :: 4 - Beta
Classifier: Intended Audience :: Developers
Classifier: License :: OSI Approved :: BSD License
Classifier: Operating System :: OS Independent
Classifier: Topic :: Software Development :: Libraries
Classifier: Topic :: Home Automation
Classifier: Programming Language :: Python :: 2.7
Classifier: Programming Language :: Python :: 3.5
